goat_plugins/uniswap/__init__.py
goat_plugins/uniswap/parameters.py
goat_plugins/uniswap/service.py
goat_sdk_plugin_uniswap-0.1.2.dist-info/METADATA
goat_sdk_plugin_uniswap-0.1.2.dist-info/WHEEL
goat_sdk_plugin_uniswap-0.1.2.dist-info/RECORD
