Metadata-Version: 2.1
Name: goat-sdk-plugin-uniswap
Version: 0.1.2
Summary: Goat plugin for uniswap
Home-page: https://ohmygoat.dev/
Keywords: goat,sdk,agents,ai,uniswap
Author: Your Name
Author-email: your_email@example.com
Requires-Python: >=3.10,<4.0
Classifier: Programming Language :: Python :: 3
Classifier: Programming Language :: Python :: 3.10
Classifier: Programming Language :: Python :: 3.11
Classifier: Programming Language :: Python :: 3.12
Requires-Dist: aiohttp (>=3.0,<4.0)
Requires-Dist: goat-sdk (>=0.1.0,<0.2.0)
Requires-Dist: goat-sdk-plugin-erc20 (>=0.1.0,<0.2.0)
Requires-Dist: goat-sdk-wallet-evm (>=0.1.1,<0.2.0)
Requires-Dist: goat-sdk-wallet-web3 (>=0.1.3,<0.2.0)
Project-URL: Bug Tracker, https://github.com/goat-sdk/goat/issues
Project-URL: Repository, https://github.com/goat-sdk/goat
